blanc_basic_pages/__init__.py
blanc_basic_pages/admin.py
blanc_basic_pages/apps.py
blanc_basic_pages/context_processors.py
blanc_basic_pages/forms.py
blanc_basic_pages/middleware.py
blanc_basic_pages/models.py
blanc_basic_pages/tests.py
blanc_basic_pages/views.py
blanc_basic_pages/migrations/0001_initial.py
blanc_basic_pages/migrations/0002_page_hero_image.py
blanc_basic_pages/migrations/__init__.py
blanc_basic_pages/templatetags/__init__.py
blanc_basic_pages/templatetags/page_tags.py
blanc_basic_pages-0.3.7.dist-info/DESCRIPTION.rst
blanc_basic_pages-0.3.7.dist-info/METADATA
blanc_basic_pages-0.3.7.dist-info/RECORD
blanc_basic_pages-0.3.7.dist-info/WHEEL
blanc_basic_pages-0.3.7.dist-info/metadata.json
blanc_basic_pages-0.3.7.dist-info/top_level.txt
