Metadata-Version: 2.0
Name: blanc-basic-pages
Version: 0.3.7
Summary: Blanc Basic Pages for Django
Home-page: https://github.com/blancltd/blanc-basic-pages
Author: Blanc Ltd
Author-email: studio@blanc.ltd.uk
License: BSD
Platform: any
Classifier: Environment :: Web Environment
Classifier: Framework :: Django
Classifier: License :: OSI Approved :: BSD License
Classifier: Operating System :: OS Independent
Classifier: Programming Language :: Python
Classifier: Programming Language :: Python :: 2
Classifier: Programming Language :: Python :: 2.7
Classifier: Programming Language :: Python :: 3
Classifier: Programming Language :: Python :: 3.3
Classifier: Programming Language :: Python :: 3.4
Classifier: Programming Language :: Python :: 3.5
Requires-Dist: blanc-basic-assets (>=0.3.2)
Requires-Dist: django-mptt (>=0.6.1)
Requires-Dist: django-mptt-admin (>=0.1.8)
